skill_upd/__init__.py
skill_upd-0.1.1.dist-info/METADATA
skill_upd-0.1.1.dist-info/WHEEL
skill_upd-0.1.1.dist-info/entry_points.txt
skill_upd-0.1.1.dist-info/RECORD
