Metadata-Version: 2.4
Name: skill-upd
Version: 0.1.1
Summary: Update Claude Code skills from GitHub to your project
License-Expression: MIT
Requires-Python: >=3.10
Requires-Dist: agent-skills-upd>=0.0.2
